{"name":"Welcome!","tagline":"nanos gigantum humeris insidentes","body":"### Bio\r\n\r\nI am a software engineer living in San Francisco.\r\n\r\nI am currently working at Xtime as an Integration Engineer.\r\n\r\nMy wife is the lovely and talented [Nancy Jeng](http://www.nancyjeng.com/)\r\n\r\n\r\n***\r\n\r\n### Projects I am proud of\r\n\r\n[A Minesweeper clone in javascript using Meteor](http://brettminesweeper.meteor.com/)\r\n\r\n\r\n[A Hailstone Sequence Calculator/Visualization using Meteor and D3.js](http://hailstone.meteor.com/)\r\n\r\n\r\n[A simple Blackjack game using Spring MVC](http://brettsblackjack.heroku.com/)\r\n\r\n\r\n[A Pomodoro Timer using the Yo API](http://pomodoryo.herokuapp.com/)\r\n\r\n\r\n[A Pogs Physics demo using Unity3d](http://173.203.123.188/)\r\n\r\n### In progress\r\n\r\n[Funder](http://funder.herokuapp.com)\r\n\r\n\r\n[A Yo based game](http://yotempole.herokuapp.com/)\r\n\r\n***\r\n\r\n### Good things\r\nhttp://thecodelesscode.com/\r\n\r\nhttp://news.ycombinator.com/\r\n\r\nhttp://www.spotify.com/us/\r\n\r\nhttp://www.catan.com/\r\n\r\n***\r\n\r\n### Contact\r\nFind me on Twitter: @thebrettdsf\r\n\r\nEmail me: the brett d at gmail.com\r\n\r\nI accept bitcoin: 1M39uoCtcP5fpT7uoM9zj39SVHd4vmzMNk\r\n\r\nThanks [Coindesk](http://coinbase.com)","google":"","note":"Don't delete this file! It's used internally to help with page regeneration."}